README.md
_wikicurses
setup.py
wikicurses.1
wikicurses.conf
wikicurses.conf.5
Wikicurses.egg-info/PKG-INFO
Wikicurses.egg-info/SOURCES.txt
Wikicurses.egg-info/dependency_links.txt
Wikicurses.egg-info/entry_points.txt
Wikicurses.egg-info/requires.txt
Wikicurses.egg-info/top_level.txt
wikicurses/__init__.py
wikicurses/__main__.py
wikicurses/htmlparse.py
wikicurses/main.py
wikicurses/settings.py
wikicurses/wiki.py