Metadata-Version: 1.1
Name: Wikicurses
Version: 1.4
Summary: A simple curses interface for accessing Wikipedia.
Home-page: http://github.com/ids1024/wikicurses/
Author: Ian D. Scott
Author-email: ian@perebruin.com
License: MIT
Platform: UNKNOWN
Classifier: Topic :: Internet :: WWW/HTTP
Classifier: Environment :: Console
Classifier: Environment :: Console :: Curses
Classifier: Operating System :: POSIX :: Linux
Classifier: Intended Audience :: End Users/Desktop
Classifier: Programming Language :: Python
Classifier: Programming Language :: Python :: 3
Classifier: Programming Language :: Python :: 3.4
Classifier: Programming Language :: Python :: 3 :: Only
Classifier: Development Status :: 5 - Production/Stable
Classifier: License :: OSI Approved :: MIT License
